BMI160_i2c/__init__.py
BMI160_i2c/commands.py
BMI160_i2c/definitions.py
BMI160_i2c/registers.py
BMI160_i2c/sleep.py
BMI160_i2c-0.6.dist-info/LICENSE
BMI160_i2c-0.6.dist-info/METADATA
BMI160_i2c-0.6.dist-info/WHEEL
BMI160_i2c-0.6.dist-info/top_level.txt
BMI160_i2c-0.6.dist-info/RECORD
