Metadata-Version: 2.1
Name: BMI160-i2c
Version: 0.6
Summary: A I2C driver library to use the BMI160 sensor (acclerometer/gyro) with python on a raspberrypi
Home-page: https://github.com/lefuturiste/BMI160-i2c
Author: Matthieu Bessat - lefuturiste
Author-email: contact@lefuturiste.fr
License: UNKNOWN
Keywords: python lefuturiste driver BMI160 acclerometer gyroscope gyro BMI bosch sensortech smbus2 sensor library i2c
Platform: UNKNOWN
Classifier: Programming Language :: Python :: 3
Classifier: License :: OSI Approved :: MIT License
Classifier: Intended Audience :: Developers
Classifier: Topic :: Software Development :: Libraries
Classifier: Topic :: System :: Hardware
Requires-Python: >=3.6
License-File: LICENSE
Requires-Dist: smbus2
